district42_exp_types/__init__.py
district42_exp_types/py.typed
district42_exp_types/ci_multi_dict/__init__.py
district42_exp_types/ci_multi_dict/_ci_multi_dict_generator.py
district42_exp_types/ci_multi_dict/_ci_multi_dict_representor.py
district42_exp_types/ci_multi_dict/_ci_multi_dict_schema.py
district42_exp_types/ci_multi_dict/_ci_multi_dict_substitutor.py
district42_exp_types/ci_multi_dict/_ci_multi_dict_validator.py
district42_exp_types/ci_multi_dict/_utils.py
district42_exp_types/multi_dict/__init__.py
district42_exp_types/multi_dict/_multi_dict_generator.py
district42_exp_types/multi_dict/_multi_dict_representor.py
district42_exp_types/multi_dict/_multi_dict_schema.py
district42_exp_types/multi_dict/_multi_dict_substitutor.py
district42_exp_types/multi_dict/_multi_dict_validator.py
district42_exp_types/multi_dict/_utils.py
district42_exp_types/numeric/__init__.py
district42_exp_types/numeric/_numeric_generator.py
district42_exp_types/numeric/_numeric_representor.py
district42_exp_types/numeric/_numeric_schema.py
district42_exp_types/numeric/_numeric_substitutor.py
district42_exp_types/numeric/_numeric_validator.py
district42_exp_types/sdict/__init__.py
district42_exp_types/sdict/_rollout.py
district42_exp_types/sdict/_sdict_generator.py
district42_exp_types/sdict/_sdict_representor.py
district42_exp_types/sdict/_sdict_schema.py
district42_exp_types/sdict/_sdict_substitutor.py
district42_exp_types/sdict/_sdict_validator.py
district42_exp_types/unordered/__init__.py
district42_exp_types/unordered/_unordered_generator.py
district42_exp_types/unordered/_unordered_representor.py
district42_exp_types/unordered/_unordered_schema.py
district42_exp_types/unordered/_unordered_substitutor.py
district42_exp_types/unordered/_unordered_validator.py
district42_exp_types/uuid/__init__.py
district42_exp_types/uuid/_uuid_generator.py
district42_exp_types/uuid/_uuid_representor.py
district42_exp_types/uuid/_uuid_schema.py
district42_exp_types/uuid/_uuid_substitutor.py
district42_exp_types-1.0.1.dist-info/licenses/LICENSE.txt
district42_exp_types-1.0.1.dist-info/METADATA
district42_exp_types-1.0.1.dist-info/WHEEL
district42_exp_types-1.0.1.dist-info/top_level.txt
district42_exp_types-1.0.1.dist-info/RECORD
